wordlesolve/__init__.py
wordlesolve/__main__.py
wordlesolve/console.py
wordlesolve/ruleset.py
wordlesolve/solver.py
wordlesolve/wordlist.py
wordlesolve-0.1.1.dist-info/LICENSE
wordlesolve-0.1.1.dist-info/METADATA
wordlesolve-0.1.1.dist-info/WHEEL
wordlesolve-0.1.1.dist-info/top_level.txt
wordlesolve-0.1.1.dist-info/RECORD
