Metadata-Version: 2.1
Name: wordlesolve
Version: 0.1.1
Summary: wordlesolve solves Wordle!
Home-page: https://github.com/neilmartin12/wordlesolve
Author: Neil Martin
Author-email: neilmartin12@me.com
License: UNKNOWN
Platform: UNKNOWN
Classifier: Programming Language :: Python :: 3
Classifier: License :: OSI Approved :: MIT License
Classifier: Operating System :: OS Independent
Requires-Python: >=3.9
License-File: LICENSE
Requires-Dist: wordfreq
Requires-Dist: colorama
